{
  "meta": {
    "lastUpdated": "2026-02-06T01:50:11.519Z",
    "targetDateLabel": "2月5日分",
    "rangeLabel": "1月27日〜2月5日"
  },
  "wordCloud": [
    {
      "text": "外交・安保政策",
      "score": 40
    },
    {
      "text": "外国人政策",
      "score": 21
    },
    {
      "text": "教育・子育て支援",
      "score": 18
    },
    {
      "text": "景気・物価高対策",
      "score": 100
    },
    {
      "text": "原発・エネルギー政策",
      "score": 12
    },
    {
      "text": "ジェンダー・多様性",
      "score": 73
    },
    {
      "text": "政治とカネ",
      "score": 5
    },
    {
      "text": "年金・社会保障",
      "score": 51
    },
    {
      "text": "旧統一教会",
      "score": 4
    },
    {
      "text": "衆院選の是非",
      "score": 3
    }
  ],
  "pie": {
    "外交・安保政策": [
      {
        "label": "日中関係",
        "percent": 6.2
      },
      {
        "label": "防衛力",
        "percent": 19.9
      },
      {
        "label": "憲法改正",
        "percent": 27.5
      },
      {
        "label": "日米関係",
        "percent": 4.3
      },
      {
        "label": "台湾有事",
        "percent": 11.4
      },
      {
        "label": "防衛費",
        "percent": 5.7
      },
      {
        "label": "安保三文書",
        "percent": 0
      },
      {
        "label": "非核三原則",
        "percent": 19.4
      },
      {
        "label": "拉致問題",
        "percent": 0.9
      },
      {
        "label": "スパイ防止法",
        "percent": 3.8
      },
      {
        "label": "集団的自衛権",
        "percent": 0.9
      }
    ],
    "外国人政策": [
      {
        "label": "日本人ファースト",
        "percent": 18
      },
      {
        "label": "オーバーツーリズム",
        "percent": 0.9
      },
      {
        "label": "外国人参政権",
        "percent": 1.8
      },
      {
        "label": "移民受け入れ",
        "percent": 9.9
      },
      {
        "label": "排外主義",
        "percent": 3.6
      },
      {
        "label": "不法滞在",
        "percent": 17.1
      },
      {
        "label": "強制送還",
        "percent": 10.8
      },
      {
        "label": "土葬問題",
        "percent": 0
      },
      {
        "label": "外国人土地取得",
        "percent": 6.3
      },
      {
        "label": "外国人生活保護",
        "percent": 9
      },
      {
        "label": "外国人問題",
        "percent": 22.5
      }
    ],
    "教育・子育て支援": [
      {
        "label": "教育格差",
        "percent": 4.2
      },
      {
        "label": "子ども・子育て支援金",
        "percent": 1
      },
      {
        "label": "教員不足",
        "percent": 1
      },
      {
        "label": "少子化",
        "percent": 25
      },
      {
        "label": "教育無償化",
        "percent": 8.3
      },
      {
        "label": "出産無償化",
        "percent": 3.1
      },
      {
        "label": "年少扶養控除",
        "percent": 5.2
      },
      {
        "label": "奨学金",
        "percent": 52.1
      }
    ],
    "景気・物価高対策": [
      {
        "label": "消費税",
        "percent": 23.2
      },
      {
        "label": "年収の壁",
        "percent": 1.1
      },
      {
        "label": "物価高",
        "percent": 15.8
      },
      {
        "label": "賃上げ",
        "percent": 3.3
      },
      {
        "label": "就職氷河期世代",
        "percent": 2.2
      },
      {
        "label": "非正規雇用",
        "percent": 1.9
      },
      {
        "label": "減税",
        "percent": 13.9
      },
      {
        "label": "増税",
        "percent": 7.1
      },
      {
        "label": "給付付き税額控除",
        "percent": 2
      },
      {
        "label": "円安",
        "percent": 29.4
      }
    ],
    "原発・エネルギー政策": [
      {
        "label": "原発再稼働",
        "percent": 14.3
      },
      {
        "label": "原発ゼロ",
        "percent": 1.6
      },
      {
        "label": "メガソーラー",
        "percent": 15.9
      },
      {
        "label": "温暖化対策",
        "percent": 0
      },
      {
        "label": "脱炭素",
        "percent": 17.5
      },
      {
        "label": "再生可能エネルギー",
        "percent": 50.8
      }
    ],
    "ジェンダー・多様性": [
      {
        "label": "夫婦別姓",
        "percent": 8.5
      },
      {
        "label": "同性婚",
        "percent": 2.8
      },
      {
        "label": "ジェンダー平等",
        "percent": 2.8
      },
      {
        "label": "LGBTQ",
        "percent": 83.5
      },
      {
        "label": "多文化共生",
        "percent": 2.3
      }
    ],
    "政治とカネ": [
      {
        "label": "裏金問題",
        "percent": 54.5
      },
      {
        "label": "企業・団体献金",
        "percent": 13.6
      },
      {
        "label": "政策活動費",
        "percent": 4.5
      },
      {
        "label": "議員定数削減",
        "percent": 27.3
      },
      {
        "label": "パーティ券",
        "percent": 0
      }
    ],
    "年金・社会保障": [
      {
        "label": "社会保障費削減",
        "percent": 0
      },
      {
        "label": "健康保険",
        "percent": 11.3
      },
      {
        "label": "年金",
        "percent": 63.9
      },
      {
        "label": "OTC類似薬",
        "percent": 0.4
      },
      {
        "label": "生活保護",
        "percent": 9.1
      },
      {
        "label": "介護保険",
        "percent": 5.1
      },
      {
        "label": "ベーシックサービス",
        "percent": 1.1
      },
      {
        "label": "医療費",
        "percent": 9.1
      }
    ],
    "旧統一教会": [
      {
        "label": "旧統一教会",
        "percent": 100
      }
    ],
    "衆院選の是非": [
      {
        "label": "大阪ダブル選挙",
        "percent": 50
      },
      {
        "label": "解散の大義",
        "percent": 33.3
      },
      {
        "label": "冬の選挙",
        "percent": 16.7
      }
    ]
  },
  "trends": [
    {
      "date": "2026-01-27",
      "外交・安保政策": 0.848,
      "外国人政策": 0.753,
      "教育・子育て支援": 0.456,
      "景気・物価高対策": 1,
      "原発・エネルギー政策": 0.378,
      "ジェンダー・多様性": 0.553,
      "政治と金": 0.021,
      "旧統一教会": 0.13,
      "年金・社会保障": 0.848,
      "衆院選の是非": 0.171,
      "政治とカネ": 0.128
    },
    {
      "date": "2026-01-28",
      "外交・安保政策": 0.158,
      "外国人政策": 0.111,
      "教育・子育て支援": 0.049,
      "景気・物価高対策": 0.342,
      "原発・エネルギー政策": 0.093,
      "ジェンダー・多様性": 0.043,
      "政治と金": 0.035,
      "旧統一教会": 0.064,
      "年金・社会保障": 0.136,
      "衆院選の是非": 0.016,
      "政治とカネ": 0
    },
    {
      "date": "2026-01-29",
      "外交・安保政策": 0.138,
      "外国人政策": 0.109,
      "教育・子育て支援": 0.062,
      "景気・物価高対策": 0.362,
      "原発・エネルギー政策": 0.073,
      "ジェンダー・多様性": 0.264,
      "政治と金": 0.031,
      "旧統一教会": 0.065,
      "年金・社会保障": 0.246,
      "衆院選の是非": 0.021,
      "政治とカネ": 0
    },
    {
      "date": "2026-01-30",
      "外交・安保政策": 0.116,
      "外国人政策": 0.121,
      "教育・子育て支援": 0.075,
      "景気・物価高対策": 0.515,
      "原発・エネルギー政策": 0.055,
      "ジェンダー・多様性": 0.178,
      "政治と金": 0.021,
      "旧統一教会": 0.065,
      "年金・社会保障": 0.176,
      "衆院選の是非": 0.016,
      "政治とカネ": 0
    },
    {
      "date": "2026-01-31",
      "外交・安保政策": 0.186,
      "外国人政策": 0.098,
      "教育・子育て支援": 0.066,
      "景気・物価高対策": 0.618,
      "原発・エネルギー政策": 0.04,
      "ジェンダー・多様性": 0.087,
      "政治と金": 0.043,
      "旧統一教会": 0.065,
      "年金・社会保障": 0.264,
      "衆院選の是非": 0.012,
      "政治とカネ": 0
    },
    {
      "date": "2026-02-01",
      "外交・安保政策": 0.165,
      "外国人政策": 0.099,
      "教育・子育て支援": 0.048,
      "景気・物価高対策": 0.418,
      "原発・エネルギー政策": 0.051,
      "ジェンダー・多様性": 0.09,
      "政治と金": 0.026,
      "旧統一教会": 0.053,
      "年金・社会保障": 0.138,
      "衆院選の是非": 0.015,
      "政治とカネ": 0
    },
    {
      "date": "2026-02-02",
      "外交・安保政策": 0.171,
      "外国人政策": 0.103,
      "教育・子育て支援": 0.048,
      "景気・物価高対策": 0.439,
      "原発・エネルギー政策": 0.065,
      "ジェンダー・多様性": 0.22,
      "政治と金": 0,
      "旧統一教会": 0.035,
      "年金・社会保障": 0.188,
      "衆院選の是非": 0.01,
      "政治とカネ": 0.024
    },
    {
      "date": "2026-02-03",
      "外交・安保政策": 0.166,
      "外国人政策": 0.106,
      "教育・子育て支援": 0.073,
      "景気・物価高対策": 0.784,
      "原発・エネルギー政策": 0.045,
      "ジェンダー・多様性": 0.179,
      "政治と金": 0,
      "旧統一教会": 0.036,
      "年金・社会保障": 0.11,
      "衆院選の是非": 0.012,
      "政治とカネ": 0.015
    },
    {
      "date": "2026-02-04",
      "外交・安保政策": 0.156,
      "外国人政策": 0.109,
      "教育・子育て支援": 0.081,
      "景気・物価高対策": 0.455,
      "原発・エネルギー政策": 0.064,
      "ジェンダー・多様性": 0.073,
      "政治と金": 0,
      "旧統一教会": 0.031,
      "年金・社会保障": 0.168,
      "衆院選の是非": 0.016,
      "政治とカネ": 0.026
    },
    {
      "date": "2026-02-05",
      "外交・安保政策": 0.183,
      "外国人政策": 0.096,
      "教育・子育て支援": 0.083,
      "景気・物価高対策": 0.466,
      "原発・エネルギー政策": 0.055,
      "ジェンダー・多様性": 0.337,
      "政治と金": 0,
      "旧統一教会": 0.017,
      "年金・社会保障": 0.237,
      "衆院選の是非": 0.01,
      "政治とカネ": 0.019
    }
  ]
}